{
    "$schema": "https://zed.dev/schema/themes/v0.2.0.json",
    "name": "Nord Deep",
    "author": "Nelson Monserrate",
    "themes": [
        {
            "name": "Nord Deep",
            "appearance": "dark",
            "style": {
                // editor
                "background": "#212732",
                "background.appearance": "opaque",
                "drop_target.background": "#88c0d033",
                "editor.background": "#212732",
                "editor.foreground": "#b8c5d1",
                "editor.line_number": "#434c5e",
                "editor.highlighted_line.background": "#2e344080",
                "editor.active_line.background": "#2e344080",
                "editor.active_line_number": "#b8c5d1",
                "editor.document_highlight.bracket_background": "#3b4252",
                "editor.document_highlight.read_background": "#3b4252",
                "editor.document_highlight.write_background": "#3b4252",
                "editor.gutter.background": "#212732",
                "editor.invisible": null,
                "editor.subheader.background": "#2e3440",
                "editor.wrap_guide": "#2e344080",
                "editor.active_wrap_guide": "#434c5e",
                "editor.indent_guide": "#2e344080",
                "editor.indent_guide_active": "#3b4252",
                "pane.focused_border": "#88c0d0",
                "pane_group.border": "#3b4252",
                "panel.background": "#2e3440",
                "panel.focused_border": "#88c0d0",
                "panel.indent_guide": "#3b4252",
                "panel.indent_guide_active": "#434c5e",
                "panel.indent_guide_hover": "#434c5e",
                "search.match_background": "#81a1c133",
                "elevated_surface.background": "#2e3440",
                "surface.background": "#2e3440",
                "status_bar.background": "#3b4252",
                "status_bar.foreground": "#b8c5d1",
                "tab.active_background": "#212732",
                "tab.active_foreground": "#b8c5d1",
                "tab.inactive_background": "#2e3440",
                "tab_bar.background": "#2e3440",
                "title_bar.background": "#3b4252",
                "title_bar.inactive_background": "#3b4252",
                "toolbar.background": "#212732",
                // text
                "text": "#b8c5d1",
                "text.accent": "#88c0d0",
                "text.disabled": "#798094",
                "text.muted": "#b8c5d1",
                "text.placeholder": "#798094",
                // borders
                "border": "#3b4252",
                "border.disabled": "#3b4252",
                "border.focused": "#3b4252",
                "border.selected": "#3b4252",
                "border.transparent": "#3b4252",
                "border.variant": "#3b4252",
                // elements
                "element.active": "#2e344080",
                "element.background": "#2e3440",
                "element.disabled": null,
                "element.hover": "#434c5e",
                "element.selected": "#3b4252",
                // ghost elements
                "ghost_element.active": "#2e344080",
                "ghost_element.background": null,
                "ghost_element.disabled": null,
                "ghost_element.hover": "#434c5e",
                "ghost_element.selected": "#3b4252",
                // icons
                "icon": "#b8c5d1",
                "icon.accent": "#88c0d0",
                "icon.disabled": "#798094",
                "icon.muted": "#434c5e",
                "icon.placeholder": "#798094",
                // scrollbar
                "scrollbar.thumb.background": "#3b425280",
                "scrollbar.thumb.border": "#212732",
                "scrollbar.thumb.hover_background": "#3b425280",
                "scrollbar.track.background": "#212732",
                "scrollbar.track.border": "#212732",
                // terminal
                "terminal.background": "#212732",
                "terminal.ansi.background": "#212732",
                "terminal.foreground": "#b8c5d1",
                "terminal.dim_foreground": "#798094",
                "terminal.bright_foreground": "#d4dce6",
                "terminal.ansi.foreground": "#b8c5d1",
                "terminal.ansi.black": "#3b4252",
                "terminal.ansi.red": "#bf616a",
                "terminal.ansi.green": "#a3be8c",
                "terminal.ansi.yellow": "#ebcb8b",
                "terminal.ansi.blue": "#81a1c1",
                "terminal.ansi.magenta": "#b48ead",
                "terminal.ansi.cyan": "#88c0d0",
                "terminal.ansi.white": "#b8c5d1",
                "terminal.ansi.bright_black": "#434c5e",
                "terminal.ansi.bright_red": "#bf616a",
                "terminal.ansi.bright_green": "#a3be8c",
                "terminal.ansi.bright_yellow": "#ebcb8b",
                "terminal.ansi.bright_blue": "#81a1c1",
                "terminal.ansi.bright_magenta": "#b48ead",
                "terminal.ansi.bright_cyan": "#88c0d0",
                "terminal.ansi.bright_white": "#d4dce6",
                "terminal.ansi.dim_black": null,
                "terminal.ansi.dim_red": null,
                "terminal.ansi.dim_green": null,
                "terminal.ansi.dim_yellow": null,
                "terminal.ansi.dim_blue": null,
                "terminal.ansi.dim_magenta": null,
                "terminal.ansi.dim_cyan": null,
                "terminal.ansi.dim_white": null,
                "terminal.ansi.amber": "#d08770",
                // color
                "error": "#bf616a",
                "error.background": "#bf616a40",
                "error.border": "#bf616a",
                "hint": "#5e81ac",
                "hint.background": "#5e81ac40",
                "hint.border": "#5e81ac",
                "info": "#5e81ac",
                "info.background": "#5e81ac40",
                "info.border": "#5e81ac",
                "link_text.hover": "#88c0d0",
                "predictive": "#798094",
                "predictive.background": "#212732",
                "predictive.border": "#212732",
                "renamed": "#ebcb8b",
                "renamed.background": "#ebcb8b40",
                "renamed.border": "#ebcb8b",
                "success": "#a3be8c",
                "success.background": "#a3be8c40",
                "success.border": "#a3be8c",
                "unreachable": "#d4dce6",
                "unreachable.background": "#bf616a",
                "unreachable.border": "#bf616a",
                "warning": "#ebcb8b",
                "warning.background": "#ebcb8b40",
                "warning.border": "#ebcb8b",
                // git
                "conflict": "#bf616a",
                "conflict.background": null,
                "conflict.border": null,
                "created": "#a3be8c",
                "created.background": null,
                "created.border": null,
                "deleted": "#bf616a",
                "deleted.background": null,
                "deleted.border": null,
                "hidden": "#798094",
                "hidden.background": null,
                "hidden.border": null,
                "ignored": "#798094",
                "ignored.background": null,
                "ignored.border": null,
                "modified": "#ebcb8b",
                "modified.background": null,
                "modified.border": null,
                "version_control.added": "#a3be8c",
                "version_control.added_background": "#a3be8c26",
                "version_control.conflict": "#bf616a",
                "version_control.conflict_background": "#bf616a26",
                "version_control.deleted": "#bf616a",
                "version_control.deleted_background": "#bf616a26",
                "version_control.ignored": "#798094",
                "version_control.modified": "#ebcb8b",
                "version_control.modified_background": "#ebcb8b26",
                "version_control.renamed": "#ebcb8b",
                // players
                "players": [
                    {
                        "background": "#b8c5d1",
                        "cursor": "#b8c5d1",
                        "selection": "#3b4252"
                    }
                ],
                "syntax": {
                    "attribute": {
                        "color": "#b8c5d1"
                    },
                    "boolean": {
                        "color": "#81a1c1"
                    },
                    "character": {
                        "color": "#5e81ac"
                    },
                    "character.special": {
                        "color": "#d08770"
                    },
                    "comment": {
                        "color": "#798094"
                    },
                    "comment.doc": {
                        "color": "#798094"
                    },
                    "comment.documentation": {
                        "color": "#798094"
                    },
                    "comment.error": {
                        "color": "#bf616a"
                    },
                    "comment.hint": {
                        "color": "#5e81ac"
                    },
                    "comment.note": {
                        "color": "#798094"
                    },
                    "comment.todo": {
                        "color": "#5e81ac"
                    },
                    "comment.warning": {
                        "color": "#ebcb8b"
                    },
                    "concept": {
                        "color": "#5e81ac"
                    },
                    "constant": {
                        "color": "#b8c5d1"
                    },
                    "constant.builtin": {
                        "color": "#81a1c1"
                    },
                    "constant.macro": {
                        "color": "#b8c5d1"
                    },
                    "constructor": {
                        "color": "#8fbcbb"
                    },
                    "diff.delta": {
                        "color": "#ebcb8b"
                    },
                    "diff.minus": {
                        "color": "#bf616a"
                    },
                    "diff.plus": {
                        "color": "#a3be8c"
                    },
                    "decorator": {
                        "color": "#b8c5d1"
                    },
                    "editor.foreground": {
                        "color": "#b8c5d1"
                    },
                    "embedded": {
                        "color": "#88c0d0"
                    },
                    "emphasis": {
                        "color": "#d4dce6",
                        "font_style": "italic",
                        "font_weight": null
                    },
                    "emphasis.strong": {
                        "color": "#d4dce6",
                        "font_style": null,
                        "font_weight": 700
                    },
                    "enum": {
                        "color": "#8fbcbb"
                    },
                    "error": {
                        "color": "#bf616a"
                    },
                    "field": {
                        "color": "#b8c5d1"
                    },
                    "float": {
                        "color": "#b48ead"
                    },
                    "function": {
                        "color": "#88c0d0"
                    },
                    "function.builtin": {
                        "color": "#88c0d0"
                    },
                    "function.call": {
                        "color": "#88c0d0"
                    },
                    "function.decorator": {
                        "color": "#b8c5d1"
                    },
                    "function.macro": {
                        "color": "#88c0d0"
                    },
                    "function.method": {
                        "color": "#88c0d0"
                    },
                    "function.method.call": {
                        "color": "#88c0d0"
                    },
                    "function.special.definition": {
                        "color": "#88c0d0"
                    },
                    "hint": {
                        "color": "#5e81ac"
                    },
                    "keyword": {
                        "color": "#81a1c1"
                    },
                    "keyword.conditional": {
                        "color": "#81a1c1"
                    },
                    "keyword.conditional.ternary": {
                        "color": "#81a1c1"
                    },
                    "keyword.coroutine": {
                        "color": "#81a1c1"
                    },
                    "keyword.debug": {
                        "color": "#81a1c1"
                    },
                    "keyword.directive": {
                        "color": "#81a1c1"
                    },
                    "keyword.directive.define": {
                        "color": "#81a1c1"
                    },
                    "keyword.exception": {
                        "color": "#81a1c1"
                    },
                    "keyword.export": {
                        "color": "#81a1c1"
                    },
                    "keyword.function": {
                        "color": "#81a1c1"
                    },
                    "keyword.import": {
                        "color": "#81a1c1"
                    },
                    "keyword.modifier": {
                        "color": "#81a1c1"
                    },
                    "keyword.operator": {
                        "color": "#81a1c1"
                    },
                    "keyword.repeat": {
                        "color": "#81a1c1"
                    },
                    "keyword.return": {
                        "color": "#81a1c1"
                    },
                    "keyword.type": {
                        "color": "#81a1c1"
                    },
                    "label": {
                        "color": "#81a1c1"
                    },
                    "link_text": {
                        "color": "#88c0d0"
                    },
                    "link_uri": {
                        "color": "#88c0d0"
                    },
                    "module": {
                        "color": "#b8c5d1"
                    },
                    "namespace": {
                        "color": "#b8c5d1"
                    },
                    "number": {
                        "color": "#b48ead"
                    },
                    "number.float": {
                        "color": "#b48ead"
                    },
                    "operator": {
                        "color": "#81a1c1"
                    },
                    "parameter": {
                        "color": "#b8c5d1"
                    },
                    "parent": {
                        "color": "#5e81ac"
                    },
                    "predictive": {
                        "color": "#b8c5d1"
                    },
                    "preproc": {
                        "color": "#5e81ac"
                    },
                    "primary": {
                        "color": "#88c0d0"
                    },
                    "property": {
                        "color": "#8fbcbb"
                    },
                    "property.json_key": {
                        "color": "#8fbcbb"
                    },
                    "punctuation": {
                        "color": "#b8c5d1"
                    },
                    "punctuation.bracket": {
                        "color": "#81a1c1"
                    },
                    "punctuation.delimiter": {
                        "color": "#81a1c1"
                    },
                    "punctuation.list_marker": {
                        "color": "#b8c5d1"
                    },
                    "punctuation.special": {
                        "color": "#81a1c1"
                    },
                    "punctuation.special.symbol": {
                        "color": "#81a1c1"
                    },
                    "string": {
                        "color": "#a3be8c"
                    },
                    "string.doc": {
                        "color": "#a3be8c"
                    },
                    "string.documentation": {
                        "color": "#a3be8c"
                    },
                    "string.escape": {
                        "color": "#ebcb8b"
                    },
                    "string.regex": {
                        "color": "#ebcb8b"
                    },
                    "string.regexp": {
                        "color": "#ebcb8b"
                    },
                    "string.special": {
                        "color": "#a3be8c"
                    },
                    "string.special.path": {
                        "color": "#a3be8c"
                    },
                    "string.special.symbol": {
                        "color": "#a3be8c"
                    },
                    "string.special.url": {
                        "color": "#88c0d0"
                    },
                    "symbol": {
                        "color": "#b48ead"
                    },
                    "tag": {
                        "color": "#81a1c1"
                    },
                    "tag.attribute": {
                        "color": "#81a1c1"
                    },
                    "tag.delimiter": {
                        "color": "#81a1c1"
                    },
                    "tag.doctype": {
                        "color": "#5e81ac"
                    },
                    "text": {
                        "color": "#b8c5d1"
                    },
                    "text.literal": {
                        "color": "#8fbcbb"
                    },
                    "title": {
                        "color": "#88c0d0"
                    },
                    "type": {
                        "color": "#8fbcbb"
                    },
                    "type.builtin": {
                        "color": "#8fbcbb"
                    },
                    "type.class.definition": {
                        "color": "#8fbcbb"
                    },
                    "type.definition": {
                        "color": "#8fbcbb"
                    },
                    "type.interface": {
                        "color": "#8fbcbb"
                    },
                    "type.super": {
                        "color": "#8fbcbb"
                    },
                    "variable": {
                        "color": "#b8c5d1"
                    },
                    "variable.builtin": {
                        "color": "#b8c5d1"
                    },
                    "variable.member": {
                        "color": "#b8c5d1"
                    },
                    "variable.parameter": {
                        "color": "#b8c5d1"
                    },
                    "variable.special": {
                        "color": "#b8c5d1"
                    },
                    "variant": {
                        "color": "#8fbcbb"
                    },
                    "warning": {
                        "color": "#ebcb8b"
                    }
                }
            }
        }
    ]
}
